Workbook

Sheet Team 8 Analysis
A1: EV Chargers at Costco | B1: Initial Cash
B2: Outflow | C2: Year 1 | D2: Year 2 | E2: Year 3 | F2: Year 4 | G2: Year 5 | H2: Year 6 | I2: Year 7 | J2: Year 8 | K2: Year 9 | L2: Year 10
A3: Charger Unit and Service Upgrades | B3: =-('Assumptions and Initial Numbers'!H2+'Assumptions and Initial Numbers'!H3)*'Assumptions and Initial Numbers'!E15 -> -51445715
A4: Shipping / Delivery | B4: =-'Assumptions and Initial Numbers'!H7*'Assumptions and Initial Numbers'!E15 -> -2509547.1
A5: Private Label Fee | B5: =B31 -> -37643206
A6: Installation and Labor | B6: =-'Assumptions and Initial Numbers'!H4*'Assumptions and Initial Numbers'!E15 -> -20076377
A7: Permits and Inspections | B7: =-'Assumptions and Initial Numbers'!H5*'Assumptions and Initial Numbers'!E15 -> -2509547.1
A8: Site Prep and Cabling | B8: =-'Assumptions and Initial Numbers'!H6*'Assumptions and Initial Numbers'!E15 -> -10038188
A9: Subtotal Startup/Finish | B9: =SUM(B3:B8) -> -1.2422258e+08 | C9: =+C3+C4+C6+C7+C8 -> 0 | D9: =+D3+D4+D6+D7+D8 -> 0 | E9: =+E3+E4+E6+E7+E8 -> 0 | F9: =+F3+F4+F6+F7+F8 -> 0 | G9: =+G3+G4+G6+G7+G8 -> 0 | H9: =+H3+H4+H6+H7+H8 -> 0 | I9: =+I3+I4+I6+I7+I8 -> 0 | J9: =+J3+J4+J6+J7+J8 -> 0 | ... L9: =+L3+L4+L6+L7+L8 -> 0
A11: New Sales | C11: =D28 -> 53470210 | D11: =C11*(1+$G$28) -> 60421338 | E11: =D11*(1+$G$28) -> 68276112 | F11: =E11*(1+$G$28) -> 77152006 | G11: =F11*(1+$G$28) -> 87181767 | H11: =G11*(1+$G$28) -> 98515397 | I11: =H11*(1+$G$28) -> 1.113224e+08 | J11: =I11*(1+$G$28) -> 1.2579431e+08 | K11: =J11*(1+$G$28) -> 1.4214757e+08 | L11: =K11*(1+$G$28) -> 1.6062675e+08
A12: Electric Costs | C12: =-C11*B29 -> -24945469 | D12: =+C12*(1+$B$30) -> -26816379 | E12: =+D12*(1+$B$30) -> -28827608 | F12: =+E12*(1+$B$30) -> -30989678 | G12: =+F12*(1+$B$30) -> -33313904 | H12: =+G12*(1+$B$30) -> -35812447 | I12: =+H12*(1+$B$30) -> -38498380 | J12: =+I12*(1+$B$30) -> -41385759 | K12: =+J12*(1+$B$30) -> -44489691 | L12: =+K12*(1+$B$30) -> -47826418
A13: Maintenance Costs | C13: =-C11*$D$31 -> -1405346.4 | D13: =+C13*(1+$B$30) -> -1510747.3 | E13: =+D13*(1+$B$30) -> -1624053.4 | F13: =+E13*(1+$B$30) -> -1745857.4 | G13: =+F13*(1+$B$30) -> -1876796.7 | H13: =+G13*(1+$B$30) -> -2017556.5 | I13: =+H13*(1+$B$30) -> -2168873.2 | J13: =+I13*(1+$B$30) -> -2331538.7 | K13: =+J13*(1+$B$30) -> -2506404.1 | L13: =+K13*(1+$B$30) -> -2694384.4
A14: Depreciation | C14: =-$F$33 -> -10195035 | D14: =-$F$33 -> -10195035 | E14: =-$F$33 -> -10195035 | F14: =-$F$33 -> -10195035 | G14: =-$F$33 -> -10195035 | H14: =-$F$33 -> -10195035 | I14: =-$F$33 -> -10195035 | J14: =-$F$33 -> -10195035 | K14: 0 | L14: 0
A15: Earnings before Tax | C15: =SUM(C11:C14) -> 16924360 | D15: =SUM(D11:D14) -> 21899176 | E15: =SUM(E11:E14) -> 27629416 | F15: =SUM(F11:F14) -> 34221436 | G15: =SUM(G11:G14) -> 41796031 | H15: =SUM(H11:H14) -> 50490358 | I15: =SUM(I11:I14) -> 60460110 | J15: =SUM(J11:J14) -> 71881977 | ... L15: =SUM(L11:L14) -> 1.1010595e+08
A16: Taxes | C16: =-C15*$B$32 -> -3554115.6 | D16: =-D15*$B$32 -> -4598827 | E16: =-E15*$B$32 -> -5802177.3 | F16: =-F15*$B$32 -> -7186501.5 | G16: =-G15*$B$32 -> -8777166.5 | H16: =-H15*$B$32 -> -10602975 | I16: =-I15*$B$32 -> -12696623 | J16: =-J15*$B$32 -> -15095215 | ... L16: =-L15*$B$32 -> -23122250
A17: Net Income | C17: =+C15+C16 -> 13370244 | D17: =+D15+D16 -> 17300349 | E17: =+E15+E16 -> 21827238 | F17: =+F15+F16 -> 27034934 | G17: =+G15+G16 -> 33018865 | H17: =+H15+H16 -> 39887383 | I17: =+I15+I16 -> 47763487 | J17: =+J15+J16 -> 56786762 | ... L17: =+L15+L16 -> 86983702
A18: Plus Depreciation | C18: =-C14 -> 10195035 | D18: =-D14 -> 10195035 | E18: =-E14 -> 10195035 | F18: =-F14 -> 10195035 | G18: =-G14 -> 10195035 | H18: =-H14 -> 10195035 | I18: =-I14 -> 10195035 | J18: =-J14 -> 10195035 | ... L18: =-L14 -> 0
A19: Subtotal Cash Income | C19: =+C17+C18 -> 23565279 | D19: =+D17+D18 -> 27495384 | E19: =+E17+E18 -> 32022273 | F19: =+F17+F18 -> 37229969 | G19: =+G17+G18 -> 43213900 | H19: =+H17+H18 -> 50082418 | I19: =+I17+I18 -> 57958522 | J19: =+J17+J18 -> 66981797 | ... L19: =+L17+L18 -> 86983702
A23: Total Cash Flows | B23: =+B9+B19 -> -1.2422258e+08 | C23: =+C9+C19+C21 -> 23565279 | D23: =+D9+D19+D21 -> 27495384 | E23: =+E9+E19+E21 -> 32022273 | F23: =+F9+F19+F21 -> 37229969 | G23: =+G9+G19+G21 -> 43213900 | H23: =+H9+H19+H21 -> 50082418 | I23: =+I9+I19+I21 -> 57958522 | J23: =+J9+J19+J21 -> 66981797 | ... L23: =+L9+L19+L21 -> 86983702
A25: NPV | B25: =NPV(B34,C23:L23)+B23 -> 45503766 | C25: =NPV(B34,C23:L23)+B23
A26: IRR | B26: =IRR(B23:L23) -> 0.2781964 | C26: =IRR(B23:L23)
A27: Assumptions | C27: Times % TGT | D27: TGT Sales | G27: Growth Year/Year
A28: Max Potential Rev for Chargers | B28: ='Assumptions and Initial Numbers'!E23 -> 76386015 | C28: 0.7 | D28: =+B28*C28 -> 53470210 | E28: Machines | F28: ='Assumptions and Initial Numbers'!B39 -> 84069827 | G28: 0.13
A29: Electric Costs New Store | B29: ='Assumptions and Initial Numbers'!E32 -> 0.46653022 | E29: Shipping (above) | F29: =B4 -> -2509547.1
A30: Variable Cost Growth Rate | B30: =B33*2.5 -> 0.075 | E30: Total | F30: =+F28+F29 -> 81560280
A31: Private Label Fee | B31: =-(15000*'Assumptions and Initial Numbers'!E15) -> -37643206 | C31: Maintenance Costs | D31: ='Assumptions and Initial Numbers'!E36 -> 0.026282791
A32: Tax Rate | B32: 0.21
A33: Inflation | B33: 0.03 | E33: Depreciation | F33: =+F30/8 -> 10195035 | G33: 8 year life straight line (12.5%)
A34: WACC or Hurdle Rate | B34: 0.2
A36: Added Scenarios Team 8 | B36: Base | C36: +/- | D36: New # | E36: Low IRR | F36: High IRR
A37: Base Case | B37: -0.132
A39: Change % TGT Sales | B39: 0.7 | C39: 0.3 | D39: 0.4 | E39: 0.153 | F39: 0.278
A40: Growth Year/Year | B40: 0.13 | C40: 0.05 | D40: 0.08 | E40: 0.205 | F40: 0.278 | H40: With 40% of sales target and 8% growth rate
A41: Both | E41: 0.086 | F41: 0.278 | H41: this project could go

Sheet Assumptions and Initial Numbers
A1: Wawa Info | G1: Average Cost Per Charger
A2: Wawa Total Locations | B2: 1203 | D2: EV Chargers per Wawa Location in U.S. | E2: =B4/B3 -> 9.4843049 | G2: Charger Unit | H2: 12500
A3: Wawa Locations with EV Chargers | B3: 223 | D3: Total Number of Wawa EV Chargers among Specific Locations | E3: =E2*B5 -> 265.56054 | G3: Electrical Service Upgrades | H3: 8000
A4: Total EV Chargers at Wawa | B4: 2115 | D4: Cost of Total Wawa EV Chargers | E4: =E3*B15 -> 9161838.6 | G4: Electrical Installation Labor | H4: 8000
A5: Wawa Locations in Orl, Jax, Tampa, South Florida with EV Chargers | B5: =5+9+6+2+6 -> 28 | G5: Permits & Inspections | H5: 1000
A6: Typical Wawa Location Square Footage | B6: =AVERAGE(2800,4400) -> 3600 | G6: Site Prep & Cabling | H6: 4000
G7: Delivery & Logistics | H7: 1000
G8: Total Cost | H8: =SUM(H2:H7) -> 34500
A9: Costco Info
A10: Total Costco Locations FL, GA, TN, AL, SC, NC | B10: =34+16+9+5+7+10 -> 81
A11: Typical Costco Location Square Footage | B11: 147000
A13: EV Charger Cost Info | D13: Costco Cost for EV fast charger
A14: Cost of private labeled EV charger | B14: =H8+B16 -> 49500 | D14: Costco/Wawa Square Footage | E14: =B11/B6 -> 40.833333
A15: Cost of Tesla EV Charger | B15: =H8 -> 34500 | D15: Assumption of Total Costco Chargers in FL | E15: =(B10*E2*E14)*8% -> 2509.5471
A16: Estimated Additional Cost of Private Labeling per Charger | B16: 15000 | D16: Assumption of Costco Chargers in FL per Store | E16: =E15/B10 -> 30.982063
D17: Total Chargers, All Locations | E17: =E16*B10 -> 2509.5471
D18: Total Cost for Costco EV Chargers | E18: =E17*B14 -> 1.2422258e+08
A21: Tesla Charger Info | D21: Revenue
A22: Total Chargers in US as of 2025 | B22: 75000 | D22: Wawa Revenue for All Locations | E22: =B26*E3 -> 9001851.6
A23: Average Daily Throughput per Stall kWh | B23: 251 | D23: Costco Potential Revenue First Year after Input of Chargers | E23: =B34*E17 -> 76386015
A24: Throughput per Stall per Year | B24: =B23*365 -> 91615
A25: Price Wawa Charges for kWh | B25: 0.37
A26: Revenue from One Stall per Year | B26: =B24*B25 -> 33897.55
A28: Gas Info | D28: Variable Costs
A29: Costco Gas Discount | B29: 0.18 | D29: Florida Average Electricity Rate | E29: 0.155
A30: Gas Price | B30: 3.75 | D30: Cost per Charger for Costco | E30: =E29*B24 -> 14200.325
A31: Costco Gas Price | B31: =B30-B29 -> 3.57 | D31: Cost for All Costco Chargers per Year | E31: =E30*E15 -> 35636384
A32: Discount Percentage | B32: =B31/B30 -> 0.952 | D32: Electric Cost to Revenue Percentage | E32: =E31/E23 -> 0.46653022
A33: Costco kWh Price with Member Discount | B33: =(B32*B25)-0.02 -> 0.33224
A34: Costco Revenue per Stall per Year | B34: =B33*B24 -> 30438.168 | D34: Average Maintenance Costs Per Charger Per Year | E34: 800
D35: Maintenance Costs for All Costco Chargers | E35: =E34*E15 -> 2007637.7
D36: Maintenance Costs to Revenue Percentage | E36: =E35/E23 -> 0.026282791
A37: Depreciation
A38: Cost of Machine | B38: =SUM(H2:H6) -> 33500 | D38: Total Variable Costs | E38: =E35+E31 -> 37644022
A39: Total Depreciation | B39: =B38*E15 -> 84069827 | D39: Variable Costs as a Percentage of Revenue | E39: =E38/E23 -> 0.49281301
